sast_energy_monitor/__init__.py
sast_energy_monitor/cli.py
sast_energy_monitor/configs/.bandit
sast_energy_monitor/configs/.bandit_basic
sast_energy_monitor/configs/semgrep.yml
sast_energy_monitor-0.1.5.dist-info/licenses/LICENSE
sast_energy_monitor-0.1.5.dist-info/METADATA
sast_energy_monitor-0.1.5.dist-info/WHEEL
sast_energy_monitor-0.1.5.dist-info/entry_points.txt
sast_energy_monitor-0.1.5.dist-info/top_level.txt
sast_energy_monitor-0.1.5.dist-info/RECORD
