Metadata-Version: 2.4
Name: sast-energy-monitor
Version: 0.1.5
Summary: A CLI tool to measure energy consumption of Bandit and Semgrep scans using Energibridge.
Author-email: Yulin Chen <yulinchen@tudelft.nl>, Ayush Kuruvilla <akuruvilla@tudelft.nl>, Sahar Marossi <s.marossi@student.tudelft.nl>, Andrea Onofrei <a.onofrei@tudelft.nl>
License: # LICENSE
Project-URL: Homepage, https://github.com/yulinchen03/SAST-energy-monitor
Project-URL: Bug Tracker, https://github.com/yulinchen03/SAST-energy-monitor/issues
Project-URL: Repository, https://github.com/yulinchen03/SAST-energy-monitor.git
Keywords: energy,consumption,monitor,bandit,semgrep,static analysis,green software,sustainable software,energibridge,cli
Classifier: Programming Language :: Python :: 3
Classifier: Programming Language :: Python :: 3.8
Classifier: Programming Language :: Python :: 3.9
Classifier: Programming Language :: Python :: 3.10
Classifier: Programming Language :: Python :: 3.11
Classifier: Programming Language :: Python :: 3.12
Classifier: License :: OSI Approved :: MIT License
Classifier: Operating System :: OS Independent
Classifier: Environment :: Console
Classifier: Topic :: Software Development :: Quality Assurance
Classifier: Topic :: Utilities
Classifier: Topic :: System :: Monitoring
Classifier: Intended Audience :: Developers
Classifier: Development Status :: 4 - Beta
Requires-Python: >=3.8
License-File: LICENSE
Requires-Dist: colorama>=0.4.6
Dynamic: license-file
